lab06/rx.sv
// modulo receptor UART

module rx(
    input logic clk,
    input logic tick,
    input logic rx,
    output logic [7:0] data_out,
    output logic done
);

    logic [3:0] bit_cnt = 0;
    logic [9:0] shift_reg = 0;
    logic receiving = 0;

    always_ff @(posedge clk) begin
        if (!receiving && !rx) begin
            receiving <= 1;
            bit_cnt <= 0;
            done <= 0;
        end else if (tick && receiving) begin
            shift_reg <= {shift_reg[8:0], rx};
            bit_cnt <= bit_cnt + 1;

            if (bit_cnt == 9) begin
                receiving <= 0;
                data_out <= shift_reg[8:1]; // Assumindo que posição 0 = start, 9 = paridade
                done <= 1;
            end else begin
                done <= 0;
            end
        end else begin
            done <= 0;
        end
    end
endmodule

lab06/tx.sv
// modulo transmissor UART

module tx(
    input  logic clk,        
    input  logic tick,       // Tick de baud rate (ex: 9600Hz)
    input  logic send,       // Sinal para iniciar transmissão
    input  logic [7:0]  data_in, // Byte de dados
    output logic tx,         // Linha TX
    output logic busy        // Indica transmissão em andamento
);

    logic [3:0] bit_cnt = 0;
    logic [9:0] shift_reg = 10'b1111111111;  // Linha ociosa = 1
    logic sending = 0;

    // Função para calcular paridade par
    function logic calc_parity(input [7:0] data);
        calc_parity = ~^data;  // XOR de todos os bits e inverte (paridade par)
    endfunction

    always_ff @(posedge clk) begin
        if (send && !sending) begin
            shift_reg <= {1'b1,  data_in,  calc_parity(data_in), 1'b0}; // STOP | PAR | DATA | START
            bit_cnt   <= 0;
            sending   <= 1;
            busy      <= 1;
            tx        <= 0; // START bit
        end
        else if (tick && sending) begin
            tx        <= shift_reg[0];
            shift_reg <= shift_reg >> 1;
            bit_cnt   <= bit_cnt + 1;

            if (bit_cnt == 9) begin
                sending <= 0;
                busy    <= 0;
                tx      <= 1; // Linha idle após fim
            end
        end else if (!sending) begin
            tx <= 1; // idle
        end
    end


endmodule

lab06/div_clock.sv
// modulo divisor de clock sabendo que 50 MHz / 9600 = 5208

module div_clock #(parameter DIV = 5208) (
    input logic clk,
    input logic rst,
    output logic pulse
);

    logic [$clog2(DIV)-1:0] counter;

    always_ff @(posedge clk or posedge rst) begin
        if (rst) begin
            counter <= 0;
            pulse <= 0;
        end else if (counter == DIV - 1) begin
            counter <= 0;
            pulse <= 1;
        end else begin
            counter <= counter + 1;
            pulse <= 0;
        end
    end

endmodule

lab06/uart.sv
// uart com receptor, transmissor e divisor de clock instanciados

module uart(
    input logic clk,
    input logic rst,
    input logic send,
    input logic [7:0] tx_data,
    input logic rx,
    output logic tx,
    output logic [7:0] rx_data,
    output logic tx_busy,
    output logic rx_done
);

    logic tick;

    // Divisor de Clock
    div_clock #(.DIV(5208)) clock_inst (
        .clk(clk),
        .rst(rst),
        .pulse(tick)
    );

    // Transmissor UART
    tx tx_inst (
        .clk(clk),
        .tick(tick),
        .send(send),
        .data_in(tx_data),
        .tx(tx),
        .busy(tx_busy)
    );

    // Receptor UART
    rx rx_inst (
        .clk(clk),
        .tick(tick),
        .rx(rx),
        .data_out(rx_data),
        .done(rx_done)
    );

endmodule

lab06/uart_tb.sv
`timescale 1ns / 1ps

module uart_tb();

    // Parâmetros da UART
    parameter CLK_PERIOD = 20;        // 50 MHz => 20 ns por ciclo
    parameter BAUD_RATE = 9600;
    parameter BAUD_TICK = 104_166;    // Em ns: 1/9600 s ≈ 104.166 us

    // Sinais da UART
    logic clk = 0;
    logic rst = 1;
    logic send = 0;
    logic [7:0] tx_data = 8'h00;
    logic tx;
    logic rx;
    logic [7:0] rx_data;
    logic tx_busy;
    logic rx_done;

    // Conecta TX no RX internamente (loopback)
    assign rx = tx;

    // Instancia a UART
    uart uart_inst (
        .clk(clk),
        .rst(rst),
        .send(send),
        .tx_data(tx_data),
        .rx(rx),
        .tx(tx),
        .rx_data(rx_data),
        .tx_busy(tx_busy),
        .rx_done(rx_done)
    );

    // Gera clock de 50 MHz
    always #(CLK_PERIOD/2) clk = ~clk;

    // Tarefa para enviar um byte pela UART
    task send_byte(input [7:0] data);
        begin
            @(negedge clk);
            tx_data = data;
            send = 1;
            @(negedge clk);
            send = 0;

            // Espera a transmissão terminar
            wait (tx_busy == 0);
        end
    endtask

    // Simulação principal
    initial begin
        $display("Iniciando simulacao UART...");
        $dumpfile("uart_tb.vcd");
        $dumpvars;

        // Reset
        #100;
        rst = 0;

        // Envia o byte 0xA5
        send_byte(8'hA5);
        $display("Byte enviado: 0xA5");

        // Espera o receptor sinalizar conclusão
        wait(rx_done == 1);
        @(negedge clk); // Espera um ciclo para estabilidade

        if (rx_data == 8'hA5) begin
            $display("SUCESSO! Byte recebido corretamente: %h", rx_data);
        end else begin
            $display("ERRO! Byte recebido: %h (esperado: A5)", rx_data);
        end

        #20000; // Espera extra para observação no GTKWave
        $finish;
    end

endmodule

lab06/quartus/simulation/modelsim/uart_tb.vcd
$date
	Tue May 13 20:28:08 2025
$end
$version
	ModelSim Version 10.5b
$end
$timescale
	1ps
$end

$scope module uart_tb $end
$var parameter 32 ! CLK_PERIOD $end
$var parameter 32 " BAUD_RATE $end
$var parameter 32 # BAUD_TICK $end
$var reg 1 $ clk $end
$var reg 1 % rst $end
$var reg 1 & send $end
$var reg 8 ' tx_data [7:0] $end
$var reg 1 ( tx $end
$var reg 1 ) rx $end
$var reg 8 * rx_data [7:0] $end
$var reg 1 + tx_busy $end
$var reg 1 , rx_done $end

$scope task send_byte $end
$var reg 8 - data [7:0] $end
$upscope $end

$scope module uart_inst $end
$var wire 1 . clk $end
$var wire 1 / rst $end
$var wire 1 0 send $end
$var wire 1 1 tx_data [7] $end
$var wire 1 2 tx_data [6] $end
$var wire 1 3 tx_data [5] $end
$var wire 1 4 tx_data [4] $end
$var wire 1 5 tx_data [3] $end
$var wire 1 6 tx_data [2] $end
$var wire 1 7 tx_data [1] $end
$var wire 1 8 tx_data [0] $end
$var wire 1 9 rx $end
$var reg 1 : tx $end
$var reg 8 ; rx_data [7:0] $end
$var reg 1 < tx_busy $end
$var reg 1 = rx_done $end
$var reg 1 > tick $end

$scope module clock_inst $end
$var parameter 32 ? DIV $end
$var wire 1 . clk $end
$var wire 1 / rst $end
$var reg 1 @ pulse $end
$var reg 13 A counter [12:0] $end
$upscope $end

$scope module tx_inst $end
$var wire 1 . clk $end
$var wire 1 B tick $end
$var wire 1 0 send $end
$var wire 1 1 data_in [7] $end
$var wire 1 2 data_in [6] $end
$var wire 1 3 data_in [5] $end
$var wire 1 4 data_in [4] $end
$var wire 1 5 data_in [3] $end
$var wire 1 6 data_in [2] $end
$var wire 1 7 data_in [1] $end
$var wire 1 8 data_in [0] $end
$var reg 1 C tx $end
$var reg 1 D busy $end
$var reg 4 E bit_cnt [3:0] $end
$var reg 10 F shift_reg [9:0] $end
$var reg 1 G sending $end

$scope function calc_parity $end
$var reg 1 H calc_parity $end
$var reg 8 I data [7:0] $end
$upscope $end
$upscope $end

$scope module rx_inst $end
$var wire 1 . clk $end
$var wire 1 J tick $end
$var wire 1 9 rx $end
$var reg 8 K data_out [7:0] $end
$var reg 1 L done $end
$var reg 4 M bit_cnt [3:0] $end
$var reg 10 N shift_reg [9:0] $end
$var reg 1 O receiving $end
$upscope $end
$upscope $end
$upscope $end

$scope begin std $end
$upscope $end
$enddefinitions $end
#0
$dumpvars
0$
1%
0&
b0 '
x(
x)
bx *
x+
x,
x:
bx ;
x<
x=
0>
0@
b0 A
xC
xD
b0 E
b1111111111 F
0G
xH
bx I
bx K
xL
b0 M
b0 N
0O
bx -
b10100 !
b10010110000000 "
b11001011011100110 #
b1010001011000 ?
0.
1/
00
08
07
06
05
04
03
02
01
x9
0B
0J
$end
#10000
1$
1.
1C
0L
0=
1:
1(
0,
1)
19
#20000
0$
0.
#30000
1$
1.
#40000
0$
0.
#50000
1$
1.
#60000
0$
0.
#70000
1$
1.
#80000
0$
0.
#90000
1$
1.
#100000
0%
b10100101 -
0$
0/
0.
b10100101 '
1&
18
16
13
11
10
#110000
1$
1.
b10100101 I
1H
b1 A
b1010010110 F
1G
1D
0C
0:
1<
1+
0(
0)
09
#120000
0$
0.
0&
00
#130000
1$
1.
b10 A
1O
#140000
0$
0.
#150000
1$
1.
b11 A
#160000
0$
0.
#170000
1$
1.
b100 A
#180000
0$
0.
#190000
1$
1.
b101 A
#200000
0$
0.
#210000
1$
1.
b110 A
#220000
0$
0.
#230000
1$
1.
b111 A
#240000
0$
0.
#250000
1$
1.
b1000 A
#260000
0$
0.
#270000
1$
1.
b1001 A
#280000
0$
0.
#290000
1$
1.
b1010 A
#300000
0$
0.
#310000
1$
1.
b1011 A
#320000
0$
0.
#330000
1$
1.
b1100 A
#340000
0$
0.
#350000
1$
1.
b1101 A
#360000
0$
0.
#370000
1$
1.
b1110 A
#380000
0$
0.
#390000
1$
1.
b1111 A
#400000
0$
0.
#410000
1$
1.
b10000 A
#420000
0$
0.
#430000
1$
1.
b10001 A
#440000
0$
0.
#450000
1$
1.
b10010 A
#460000
0$
0.
#470000
1$
1.
b10011 A
#480000
0$
0.
#490000
1$
1.
b10100 A
#500000
0$
0.
#510000
1$
1.
b10101 A
#520000
0$
0.
#530000
1$
1.
b10110 A
#540000
0$
0.
#550000
1$
1.
b10111 A
#560000
0$
0.
#570000
1$
1.
b11000 A
#580000
0$
0.
#590000
1$
1.
b11001 A
#600000
0$
0.
#610000
1$
1.
b11010 A
#620000
0$
0.
#630000
1$
1.
b11011 A
#640000
0$
0.
#650000
1$
1.
b11100 A
#660000
0$
0.
#670000
1$
1.
b11101 A
#680000
0$
0.
#690000
1$
1.
b11110 A
#700000
0$
0.
#710000
1$
1.
b11111 A
#720000
0$
0.
#730000
1$
1.
b100000 A
#740000
0$
0.
#750000
1$
1.
b100001 A
#760000
0$
0.
#770000
1$
1.
b100010 A
#780000
0$
0.
#790000
1$
1.
b100011 A
#800000
0$
0.
#810000
1$
1.
b100100 A
#820000
0$
0.
#830000
1$
1.
b100101 A
#840000
0$
0.
#850000
1$
1.
b100110 A
#860000
0$
0.
#870000
1$
1.
b100111 A
#880000
0$
0.
#890000
1$
1.
b101000 A
#900000
0$
0.
#910000
1$
1.
b101001 A
#920000
0$
0.
#930000
1$
1.
b101010 A
#940000
0$
0.
#950000
1$
1.
b101011 A
#960000
0$
0.
#970000
1$
1.
b101100 A
#980000
0$
0.
#990000
1$
1.
b101101 A
#1000000
0$
0.
#1010000
1$
1.
b101110 A
#1020000
0$
0.
#1030000
1$
1.
b101111 A
#1040000
0$
0.
#1050000
1$
1.
b110000 A
#1060000
0$
0.
#1070000
1$
1.
b110001 A
#1080000
0$
0.
#1090000
1$
1.
b110010 A
#1100000
0$
0.
#1110000
1$
1.
b110011 A
#1120000
0$
0.
#1130000
1$
1.
b110100 A
#1140000
0$
0.
#1150000
1$
1.
b110101 A
#1160000
0$
0.
#1170000
1$
1.
b110110 A
#1180000
0$
0.
#1190000
1$
1.
b110111 A
#1200000
0$
0.
#1210000
1$
1.
b111000 A
#1220000
0$
0.
#1230000
1$
1.
b111001 A
#1240000
0$
0.
#1250000
1$
1.
b111010 A
#1260000
0$
0.
#1270000
1$
1.
b111011 A
#1280000
0$
0.
#1290000
1$
1.
b111100 A
#1300000
0$
0.
#1310000
1$
1.
b111101 A
#1320000
0$
0.
#1330000
1$
1.
b111110 A
#1340000
0$
0.
#1350000
1$
1.
b111111 A
#1360000
0$
0.
#1370000
1$
1.
b1000000 A
#1380000
0$
0.
#1390000
1$
1.
b1000001 A
#1400000
0$
0.
#1410000
1$
1.
b1000010 A
#1420000
0$
0.
#1430000
1$
1.
b1000011 A
#1440000
0$
0.
#1450000
1$
1.
b1000100 A
#1460000
0$
0.
#1470000
1$
1.
b1000101 A
#1480000
0$
0.
#1490000
1$
1.
b1000110 A
#1500000
0$
0.
#1510000
1$
1.
b1000111 A
#1520000
0$
0.
#1530000
1$
1.
b1001000 A
#1540000
0$
0.
#1550000
1$
1.
b1001001 A
#1560000
0$
0.
#1570000
1$
1.
b1001010 A
#1580000
0$
0.
#1590000
1$
1.
b1001011 A
#1600000
0$
0.
#1610000
1$
1.
b1001100 A
#1620000
0$
0.
#1630000
1$
1.
b1001101 A
#1640000
0$
0.
#1650000
1$
1.
b1001110 A
#1660000
0$
0.
#1670000
1$
1.
b1001111 A
#1680000
0$
0.
#1690000
1$
1.
b1010000 A
#1700000
0$
0.
#1710000
1$
1.
b1010001 A
#1720000
0$
0.
#1730000
1$
1.
b1010010 A
#1740000
0$
0.
#1750000
1$
1.
b1010011 A
#1760000
0$
0.
#1770000
1$
1.
b1010100 A
#1780000
0$
0.
#1790000
1$
1.
b1010101 A
#1800000
0$
0.
#1810000
1$
1.
b1010110 A
#1820000
0$
0.
#1830000
1$
1.
b1010111 A
#1840000
0$
0.
#1850000
1$
1.
b1011000 A
#1860000
0$
0.
#1870000
1$
1.
b1011001 A
#1880000
0$
0.
#1890000
1$
1.
b1011010 A
#1900000
0$
0.
#1910000
1$
1.
b1011011 A
#1920000
0$
0.
#1930000
1$
1.
b1011100 A
#1940000
0$
0.
#1950000
1$
1.
b1011101 A
#1960000
0$
0.
#1970000
1$
1.
b1011110 A
#1980000
0$
0.
#1990000
1$
1.
b1011111 A
#2000000
0$
0.
#2010000
1$
1.
b1100000 A
#2020000
0$
0.
#2030000
1$
1.
b1100001 A
#2040000
0$
0.
#2050000
1$
1.
b1100010 A
#2060000
0$
0.
#2070000
1$
1.
b1100011 A
#2080000
0$
0.
#2090000
1$
1.
b1100100 A
#2100000
0$
0.
#2110000
1$
1.
b1100101 A
#2120000
0$
0.
#2130000
1$
1.
b1100110 A
#2140000
0$
0.
#2150000
1$
1.
b1100111 A
#2160000
0$
0.
#2170000
1$
1.
b1101000 A
#2180000
0$
0.
#2190000
1$
1.
b1101001 A
#2200000
0$
0.
#2210000
1$
1.
b1101010 A
#2220000
0$
0.
#2230000
1$
1.
b1101011 A
#2240000
0$
0.
#2250000
1$
1.
b1101100 A
#2260000
0$
0.
#2270000
1$
1.
b1101101 A
#2280000
0$
0.
#2290000
1$
1.
b1101110 A
#2300000
0$
0.
#2310000
1$
1.
b1101111 A
#2320000
0$
0.
#2330000
1$
1.
b1110000 A
#2340000
0$
0.
#2350000
1$
1.
b1110001 A
#2360000
0$
0.
#2370000
1$
1.
b1110010 A
#2380000
0$
0.
#2390000
1$
1.
b1110011 A
#2400000
0$
0.
#2410000
1$
1.
b1110100 A
#2420000
0$
0.
#2430000
1$
1.
b1110101 A
#2440000
0$
0.
#2450000
1$
1.
b1110110 A
#2460000
0$
0.
#2470000
1$
1.
b1110111 A
#2480000
0$
0.
#2490000
1$
1.
b1111000 A
#2500000
0$
0.
#2510000
1$
1.
b1111001 A
#2520000
0$
0.
#2530000
1$
1.
b1111010 A
#2540000
0$
0.
#2550000
1$
1.
b1111011 A
#2560000
0$
0.
#2570000
1$
1.
b1111100 A
#2580000
0$
0.
#2590000
1$
1.
b1111101 A
#2600000
0$
0.
#2610000
1$
1.
b1111110 A
#2620000
0$
0.
#2630000
1$
1.
b1111111 A
#2640000
0$
0.
#2650000
1$
1.
b10000000 A
#2660000
0$
0.
#2670000
1$
1.
b10000001 A
#2680000
0$
0.
#2690000
1$
1.
b10000010 A
#2700000
0$
0.
#2710000
1$
1.
b10000011 A
#2720000
0$
0.
#2730000
1$
1.
b10000100 A
#2740000
0$
0.
#2750000
1$
1.
b10000101 A
#2760000
0$
0.
#2770000
1$
1.
b10000110 A
#2780000
0$
0.
#2790000
1$
1.
b10000111 A
#2800000
0$
0.
#2810000
1$
1.
b10001000 A
#2820000
0$
0.
#2830000
1$
1.
b10001001 A
#2840000
0$
0.
#2850000
1$
1.
b10001010 A
#2860000
0$
0.
#2870000
1$
1.
b10001011 A
#2880000
0$
0.
#2890000
1$
1.
b10001100 A
#2900000
0$
0.
#2910000
1$
1.
b10001101 A
#2920000
0$
0.
#2930000
1$
1.
b10001110 A
#2940000
0$
0.
#2950000
1$
1.
b10001111 A
#2960000
0$
0.
#2970000
1$
1.
b10010000 A
#2980000
0$
0.
#2990000
1$
1.
b10010001 A
#3000000
0$
0.
#3010000
1$
1.
b10010010 A
#3020000
0$
0.
#3030000
1$
1.
b10010011 A
#3040000
0$
0.
#3050000
1$
1.
b10010100 A
#3060000
0$
0.
#3070000
1$
1.
b10010101 A
#3080000
0$
0.
#3090000
1$
1.
b10010110 A
#3100000
0$
0.
#3110000
1$
1.
b10010111 A
#3120000
0$
0.
#3130000
1$
1.
b10011000 A
#3140000
0$
0.
#3150000
1$
1.
b10011001 A
#3160000
0$
0.
#3170000
1$
1.
b10011010 A
#3180000
0$
0.
#3190000
1$
1.
b10011011 A
#3200000
0$
0.
#3210000
1$
1.
b10011100 A
#3220000
0$
0.
#3230000
1$
1.
b10011101 A
#3240000
0$
0.
#3250000
1$
1.
b10011110 A
#3260000
0$
0.
#3270000
1$
1.
b10011111 A
#3280000
0$
0.
#3290000
1$
1.
b10100000 A
#3300000
0$
0.
#3310000
1$
1.
b10100001 A
#3320000
0$
0.
#3330000
1$
1.
b10100010 A
#3340000
0$
0.
#3350000
1$
1.
b10100011 A
#3360000
0$
0.
#3370000
1$
1.
b10100100 A
#3380000
0$
0.
#3390000
1$
1.
b10100101 A
#3400000
0$
0.
#3410000
1$
1.
b10100110 A
#3420000
0$
0.
#3430000
1$
1.
b10100111 A
#3440000
0$
0.
#3450000
1$
1.
b10101000 A
#3460000
0$
0.
#3470000
1$
1.
b10101001 A
#3480000
0$
0.
#3490000
1$
1.
b10101010 A
#3500000
0$
0.
#3510000
1$
1.
b10101011 A
#3520000
0$
0.
#3530000
1$
1.
b10101100 A
#3540000
0$
0.
#3550000
1$
1.
b10101101 A
#3560000
0$
0.
#3570000
1$
1.
b10101110 A
#3580000
0$
0.
#3590000
1$
1.
b10101111 A
#3600000
0$
0.
#3610000
1$
1.
b10110000 A
#3620000
0$
0.
#3630000
1$
1.
b10110001 A
#3640000
0$
0.
#3650000
1$
1.
b10110010 A
#3660000
0$
0.
#3670000
1$
1.
b10110011 A
#3680000
0$
0.
#3690000
1$
1.
b10110100 A
#3700000
0$
0.
#3710000
1$
1.
b10110101 A
#3720000
0$
0.
#3730000
1$
1.
b10110110 A
#3740000
0$
0.
#3750000
1$
1.
b10110111 A
#3760000
0$
0.
#3770000
1$
1.
b10111000 A
#3780000
0$
0.
#3790000
1$
1.
b10111001 A
#3800000
0$
0.
#3810000
1$
1.
b10111010 A
#3820000
0$
0.
#3830000
1$
1.
b10111011 A
#3840000
0$
0.
#3850000
1$
1.
b10111100 A
#3860000
0$
0.
#3870000
1$
1.
b10111101 A
#3880000
0$
0.
#3890000
1$
1.
b10111110 A
#3900000
0$
0.
#3910000
1$
1.
b10111111 A
#3920000
0$
0.
#3930000
1$
1.
b11000000 A
#3940000
0$
0.
#3950000
1$
1.
b11000001 A
#3960000
0$
0.
#3970000
1$
1.
b11000010 A
#3980000
0$
0.
#3990000
1$
1.
b11000011 A
#4000000
0$
0.
#4010000
1$
1.
b11000100 A
#4020000
0$
0.
#4030000
1$
1.
b11000101 A
#4040000
0$
0.
#4050000
1$
1.
b11000110 A
#4060000
0$
0.
#4070000
1$
1.
b11000111 A
#4080000
0$
0.
#4090000
1$
1.
b11001000 A
#4100000
0$
0.
#4110000
1$
1.
b11001001 A
#4120000
0$
0.
#4130000
1$
1.
b11001010 A
#4140000
0$
0.
#4150000
1$
1.
b11001011 A
#4160000
0$
0.
#4170000
1$
1.
b11001100 A
#4180000
0$
0.
#4190000
1$
1.
b11001101 A
#4200000
0$
0.
#4210000
1$
1.
b11001110 A
#4220000
0$
0.
#4230000
1$
1.
b11001111 A
#4240000
0$
0.
#4250000
1$
1.
b11010000 A
#4260000
0$
0.
#4270000
1$
1.
b11010001 A
#4280000
0$
0.
#4290000
1$
1.
b11010010 A
#4300000
0$
0.
#4310000
1$
1.
b11010011 A
#4320000
0$
0.
#4330000
1$
1.
b11010100 A
#4340000
0$
0.
#4350000
1$
1.
b11010101 A
#4360000
0$
0.
#4370000
1$
1.
b11010110 A
#4380000
0$
0.
#4390000
1$
1.
b11010111 A
#4400000
0$
0.
#4410000
1$
1.
b11011000 A
#4420000
0$
0.
#4430000
1$
1.
b11011001 A
#4440000
0$
0.
#4450000
1$
1.
b11011010 A
#4460000
0$
0.
#4470000
1$
1.
b11011011 A
#4480000
0$
0.
#4490000
1$
1.
b11011100 A
#4500000
0$
0.
#4510000
1$
1.
b11011101 A
#4520000
0$
0.
#4530000
1$
1.
b11011110 A
#4540000
0$
0.
#4550000
1$
1.
b11011111 A
#4560000
0$
0.
#4570000
1$
1.
b11100000 A
#4580000
0$
0.
#4590000
1$
1.
b11100001 A
#4600000
0$
0.
#4610000
1$
1.
b11100010 A
#4620000
0$
0.
#4630000
1$
1.
b11100011 A
#4640000
0$
0.
#4650000
1$
1.
b11100100 A
#4660000
0$
0.
#4670000
1$
1.
b11100101 A
#4680000
0$
0.
#4690000
1$
1.
b11100110 A
#4700000
0$
0.
#4710000
1$
1.
b11100111 A
#4720000
0$
0.
#4730000
1$
1.
b11101000 A
#4740000
0$
0.
#4750000
1$
1.
b11101001 A
#4760000
0$
0.
#4770000
1$
1.
b11101010 A
#4780000
0$
0.
#4790000
1$
1.
b11101011 A
#4800000
0$
0.
#4810000
1$
1.
b11101100 A
#4820000
0$
0.
#4830000
1$
1.
b11101101 A
#4840000
0$
0.
#4850000
1$
1.
b11101110 A
#4860000
0$
0.
#4870000
1$
1.
b11101111 A
#4880000
0$
0.
#4890000
1$
1.
b11110000 A
#4900000
0$
0.
#4910000
1$
1.
b11110001 A
#4920000
0$
0.
#4930000
1$
1.
b11110010 A
#4940000
0$
0.
#4950000
1$
1.
b11110011 A
#4960000
0$
0.
#4970000
1$
1.
b11110100 A
#4980000
0$
0.
#4990000
1$
1.
b11110101 A
#5000000
0$
0.
#5010000
1$
1.
b11110110 A
#5020000
0$
0.
#5030000
1$
1.
b11110111 A
#5040000
0$
0.
#5050000
1$
1.
b11111000 A
#5060000
0$
0.
#5070000
1$
1.
b11111001 A
#5080000
0$
0.
#5090000
1$
1.
b11111010 A
#5100000
0$
0.
#5110000
1$
1.
b11111011 A
#5120000
0$
0.
#5130000
1$
1.
b11111100 A
#5140000
0$
0.
#5150000
1$
1.
b11111101 A
#5160000
0$
0.
#5170000
1$
1.
b11111110 A
#5180000
0$
0.
#5190000
1$
1.
b11111111 A
#5200000
0$
0.
#5210000
1$
1.
b100000000 A
#5220000
0$
0.
#5230000
1$
1.
b100000001 A
#5240000
0$
0.
#5250000
1$
1.
b100000010 A
#5260000
0$
0.
#5270000
1$
1.
b100000011 A
#5280000
0$
0.
#5290000
1$
1.
b100000100 A
#5300000
0$
0.
#5310000
1$
1.
b100000101 A
#5320000
0$
0.
#5330000
1$
1.
b100000110 A
#5340000
0$
0.
#5350000
1$
1.
b100000111 A
#5360000
0$
0.
#5370000
1$
1.
b100001000 A
#5380000
0$
0.
#5390000
1$
1.
b100001001 A
#5400000
0$
0.
#5410000
1$
1.
b100001010 A
#5420000
0$
0.
#5430000
1$
1.
b100001011 A
#5440000
0$
0.
#5450000
1$
1.
b100001100 A
#5460000
0$
0.
#5470000
1$
1.
b100001101 A
#5480000
0$
0.
#5490000
1$
1.
b100001110 A
#5500000
0$
0.
#5510000
1$
1.
b100001111 A
#5520000
0$
0.
#5530000
1$
1.
b100010000 A
#5540000
0$
0.
#5550000
1$
1.
b100010001 A
#5560000
0$
0.
#5570000
1$
1.
b100010010 A
#5580000
0$
0.
#5590000
1$
1.
b100010011 A
#5600000
0$
0.
#5610000
1$
1.
b100010100 A
#5620000
0$
0.
#5630000
1$
1.
b100010101 A
#5640000
0$
0.
#5650000
1$
1.
b100010110 A
#5660000
0$
0.
#5670000
1$
1.
b100010111 A
#5680000
0$
0.
#5690000
1$
1.
b100011000 A
#5700000
0$
0.
#5710000
1$
1.
b100011001 A
#5720000
0$
0.
#5730000
1$
1.
b100011010 A
#5740000
0$
0.
#5750000
1$
1.
b100011011 A
#5760000
0$
0.
#5770000
1$
1.
b100011100 A
#5780000
0$
0.
#5790000
1$
1.
b100011101 A
#5800000
0$
0.
#5810000
1$
1.
b100011110 A
#5820000
0$
0.
#5830000
1$
1.
b100011111 A
#5840000
0$
0.
#5850000
1$
1.
b100100000 A
#5860000
0$
0.
#5870000
1$
1.
b100100001 A
#5880000
0$
0.
#5890000
1$
1.
b100100010 A
#5900000
0$
0.
#5910000
1$
1.
b100100011 A
#5920000
0$
0.
#5930000
1$
1.
b100100100 A
#5940000
0$
0.
#5950000
1$
1.
b100100101 A
#5960000
0$
0.
#5970000
1$
1.
b100100110 A
#5980000
0$
0.
#5990000
1$
1.
b100100111 A
#6000000
0$
0.
#6010000
1$
1.
b100101000 A
#6020000
0$
0.
#6030000
1$
1.
b100101001 A
#6040000
0$
0.
#6050000
1$
1.
b100101010 A
#6060000
0$
0.
#6070000
1$
1.
b100101011 A
#6080000
0$
0.
#6090000
1$
1.
b100101100 A
#6100000
0$
0.
#6110000
1$
1.
b100101101 A
#6120000
0$
0.
#6130000
1$
1.
b100101110 A
#6140000
0$
0.
#6150000
1$
1.
b100101111 A
#6160000
0$
0.
#6170000
1$
1.
b100110000 A
#6180000
0$
0.
#6190000
1$
1.
b100110001 A
#6200000
0$
0.
#6210000
1$
1.
b100110010 A
#6220000
0$
0.
#6230000
1$
1.
b100110011 A
#6240000
0$
0.
#6250000
1$
1.
b100110100 A
#6260000
0$
0.
#6270000
1$
1.
b100110101 A
#6280000
0$
0.
#6290000
1$
1.
b100110110 A
#6300000
0$
0.
#6310000
1$
1.
b100110111 A
#6320000
0$
0.
#6330000
1$
1.
b100111000 A
#6340000
0$
0.
#6350000
1$
1.
b100111001 A
#6360000
0$
0.
#6370000
1$
1.
b100111010 A
#6380000
0$
0.
#6390000
1$
1.
b100111011 A
#6400000
0$
0.
#6410000
1$
1.
b100111100 A
#6420000
0$
0.
#6430000
1$
1.
b100111101 A
#6440000
0$
0.
#6450000
1$
1.
b100111110 A
#6460000
0$
0.
#6470000
1$
1.
b100111111 A
#6480000
0$
0.
#6490000
1$
1.
b101000000 A
#6500000
0$
0.
#6510000
1$
1.
b101000001 A
#6520000
0$
0.
#6530000
1$
1.
b101000010 A
#6540000
0$
0.
#6550000
1$
1.
b101000011 A
#6560000
0$
0.
#6570000
1$
1.
b101000100 A
#6580000
0$
0.
#6590000
1$
1.
b101000101 A
#6600000
0$
0.
#6610000
1$
1.
b101000110 A
#6620000
0$
0.
#6630000
1$
1.
b101000111 A
#6640000
0$
0.
#6650000
1$
1.
b101001000 A
#6660000
0$
0.
#6670000
1$
1.
b101001001 A
#6680000
0$
0.
#6690000
1$
1.
b101001010 A
#6700000
0$
0.
#6710000
1$
1.
b101001011 A
#6720000
0$
0.
#6730000
1$
1.
b101001100 A
#6740000
0$
0.
#6750000
1$
1.
b101001101 A
#6760000
0$
0.
#6770000
1$
1.
b101001110 A
#6780000
0$
0.
#6790000
1$
1.
b101001111 A
#6800000
0$
0.
#6810000
1$
1.
b101010000 A
#6820000
0$
0.
#6830000
1$
1.
b101010001 A
#6840000
0$
0.
#6850000
1$
1.
b101010010 A
#6860000
0$
0.
#6870000
1$
1.
b101010011 A
#6880000
0$
0.
#6890000
1$
1.
b101010100 A
#6900000
0$
0.
#6910000
1$
1.
b101010101 A
#6920000
0$
0.
#6930000
1$
1.
b101010110 A
#6940000
0$
0.
#6950000
1$
1.
b101010111 A
#6960000
0$
0.
#6970000
1$
1.
b101011000 A
#6980000
0$
0.
#6990000
1$
1.
b101011001 A
#7000000
0$
0.
#7010000
1$
1.
b101011010 A
#7020000
0$
0.
#7030000
1$
1.
b101011011 A
#7040000
0$
0.
#7050000
1$
1.
b101011100 A
#7060000
0$
0.
#7070000
1$
1.
b101011101 A
#7080000
0$
0.
#7090000
1$
1.
b101011110 A
#7100000
0$
0.
#7110000
1$
1.
b101011111 A
#7120000
0$
0.
#7130000
1$
1.
b101100000 A
#7140000
0$
0.
#7150000
1$
1.
b101100001 A
#7160000
0$
0.
#7170000
1$
1.
b101100010 A
#7180000
0$
0.
#7190000
1$
1.
b101100011 A
#7200000
0$
0.
#7210000
1$
1.
b101100100 A
#7220000
0$
0.
#7230000
1$
1.
b101100101 A
#7240000
0$
0.
#7250000
1$
1.
b101100110 A
#7260000
0$
0.
#7270000
1$
1.
b101100111 A
#7280000
0$
0.
#7290000
1$
1.
b101101000 A
#7300000
0$
0.
#7310000
1$
1.
b101101001 A
#7320000
0$
0.
#7330000
1$
1.
b101101010 A
#7340000
0$
0.
#7350000
1$
1.
b101101011 A
#7360000
0$
0.
#7370000
1$
1.
b101101100 A
#7380000
0$
0.
#7390000
1$
1.
b101101101 A
#7400000
0$
0.
#7410000
1$
1.
b101101110 A
#7420000
0$
0.
#7430000
1$
1.
b101101111 A
#7440000
0$
0.
#7450000
1$
1.
b101110000 A
#7460000
0$
0.
#7470000
1$
1.
b101110001 A
#7480000
0$
0.
#7490000
1$
1.
b101110010 A
#7500000
0$
0.
#7510000
1$
1.
b101110011 A
#7520000
0$
0.
#7530000
1$
1.
b101110100 A
#7540000
0$
0.
#7550000
1$
1.
b101110101 A
#7560000
0$
0.
#7570000
1$
1.
b101110110 A
#7580000
0$
0.
#7590000
1$
1.
b101110111 A
#7600000
0$
0.
#7610000
1$
1.
b101111000 A
#7620000
0$
0.
#7630000
1$
1.
b101111001 A
#7640000
0$
0.
#7650000
1$
1.
b101111010 A
#7660000
0$
0.
#7670000
1$
1.
b101111011 A
#7680000
0$
0.
#7690000
1$
1.
b101111100 A
#7700000
0$
0.
#7710000
1$
1.
b101111101 A
#7720000
0$
0.
#7730000
1$
1.
b101111110 A
#7740000
0$
0.
#7750000
1$
1.
b101111111 A
#7760000
0$
0.
