Lab01/ledshift.v
module ledshift (
    output wire [9:0] LEDR,  
    input [3:0] KEY,                        
    input CLOCK_50                         
);

    reg [9:0] registrador;  // Registrador para armazenar o estado dos LEDs
	 reg [2:0] detector_dir, detector_esq;
	 wire fiozinho, fiozao;
	 
	 initial begin
		registrador = 10'b0000100000;
		detector_esq = 3'b000;
		detector_dir = 3'b000;
	 end
	 
	 assign fiozinho = ~detector_dir[2] & detector_dir[1];
	 assign fiozao = ~detector_esq[2] & detector_esq[1];


	always @(posedge CLOCK_50) begin
			detector_dir <= {detector_dir[1:0], ~KEY[0]};
			detector_esq <= {detector_esq[1:0], ~KEY[3]};
	end
	 
	 
    always @(posedge CLOCK_50) begin
        if (registrador[0] == 1'b0 && fiozinho) begin
            registrador <= registrador >> 1;
        end

        if (registrador[9] == 1'b0 && fiozao) begin
            registrador <= registrador << 1;
        end

 
    end

	 
	 assign LEDR = registrador;  
endmodule

Lab01/output_files/ledshift_tb.v
`timescale 1ns / 1ps  // Define a unidade de tempo e precisão

module ledshift_tb;

    // Entradas do módulo ledshift
    reg [3:0] KEY;               // Botões de entrada
    reg CLOCK_50;                // Sinal de clock

    // Saídas do módulo ledshift
    wire [9:0] LEDR;             // LEDs de saída

    // Instanciando o módulo ledshift
    ledshift uut (
        .LEDR(LEDR),         // Saída LEDs
        .KEY(KEY),           // Entradas dos botões
        .CLOCK_50(CLOCK_50)  // Entrada de clock
    );

    // Gerador de clock
    always begin
        CLOCK_50 = 0; #10;  // Gera um sinal de clock com período de 20ns
        CLOCK_50 = 1; #10;
    end

    // Sequência de testes
    initial begin
        // Inicializa as variáveis
        KEY = 4'b1111;  // Inicializa todos os botões como "não pressionados"
        
        // Exibe o valor inicial dos LEDs
        $display("Inicializando os LEDs: %b", LEDR);
        
        // Teste 1: Pressionando KEY[0] (simula a borda de subida)
        #20;  // Aguarda 20ns para o clock
        KEY[0] = 0;  // Simula o pressionamento do botão KEY[0]
        #20;  // Aguarda mais 20ns
        KEY[0] = 1;  // Solta o botão KEY[0]

        // Teste 2: Pressionando KEY[3] (simula a borda de subida)
        #20;  // Aguarda 20ns para o clock
        KEY[3] = 0;  // Simula o pressionamento do botão KEY[3]
        #20;  // Aguarda mais 20ns
        KEY[3] = 1;  // Solta o botão KEY[3]
        
        // Teste 3: Observando o deslocamento dos LEDs
        #100;  // Aguarda 100ns para observar o comportamento

        // Teste 4: Pressionando novamente KEY[0] (outro deslocamento)
        #20;
        KEY[0] = 0;  // Pressionando o botão KEY[0]
        #20;
        KEY[0] = 1;  // Soltando o botão KEY[0]
        
        // Teste 5: Pressionando novamente KEY[3] (outro deslocamento)
        #20;
        KEY[3] = 0;  // Pressionando o botão KEY[3]
        #20;
        KEY[3] = 1;  // Soltando o botão KEY[3]

        // Teste 6: Finalizando os testes
        #100;  // Aguarda mais 100ns para observação final
        $stop;  // Interrompe a simulação
    end

endmodule

Lab01/ledshift_tb.vcd
$date
	Mon Mar 24 21:06:51 2025
$end
$version
	Icarus Verilog
$end
$timescale
	1ps
$end
$scope module ledshift_tb $end
$var wire 10 ! LEDR [9:0] $end
$var reg 1 " CLOCK_50 $end
$var reg 4 # KEY [3:0] $end
$scope module uut $end
$var wire 1 " CLOCK_50 $end
$var wire 4 $ KEY [3:0] $end
$var wire 1 % fiozao $end
$var wire 1 & fiozinho $end
$var reg 10 ' LEDR [9:0] $end
$var reg 3 ( detector_dir [2:0] $end
$var reg 3 ) detector_esq [2:0] $end
$var reg 10 * registrador [9:0] $end
$upscope $end
$upscope $end
$enddefinitions $end
$comment Show the parameter values. $end
$dumpall
$end
#0
$dumpvars
b100000 *
b0 )
bx (
b100000 '
x&
0%
b1111 $
b1111 #
0"
b100000 !
$end
#10000
bx0 (
1"
#20000
0"
#30000
0&
bx00 (
1"
#40000
0"
#50000
b1 (
1"
b1110 #
b1110 $
#60000
0"
#70000
1&
b10 (
1"
b1111 #
b1111 $
#80000
0"
#90000
0&
b100 (
b10000 *
1"
#100000
0"
#110000
b10000 !
b10000 '
b0 (
1"
#120000
0"
b111 #
b111 $
#130000
b1 )
1"
#140000
0"
b1111 #
b1111 $
#150000
1%
b10 )
1"
#160000
0"
#170000
0%
b100 )
b100000 *
1"
#180000
0"
#190000
b100000 !
b100000 '
b0 )
1"
