lab04/multiplier.sv
module multiplier #(
    parameter int N = 4 
)(
    input logic clk,
    input logic set,
    input logic [N-1:0] a, // multiplicando
    input logic [N-1:0] b, // multiplicador
    output logic [2*N-1:0] r // resultado
); 

    logic [2*N-1:0] A_ext;      // A extendido para poder shiftar (multiplicando)
    logic [N-1:0] B;            // multiplicador

    always_ff @(posedge clk) begin 
        if(set) begin
            r <= 0;
            A_ext <= a; //ele joga na parte baixa
            B <= b;  
        end else begin 
            if(B[0] == 1) begin
                r <= r + A_ext;
            end
            A_ext <= A_ext << 1; 
            B <= B >> 1;  
        end
    end
endmodule

lab04/multiplier_tb.sv
`timescale 1ns/1ps

module multiplier_tb;
    parameter int N = 4;

    logic clk;
    logic set;
    logic [N-1:0] a, b;
    logic [2*N-1:0] r;


    multiplier #(.N(N)) dut (
        .clk(clk),
        .set(set),
        .a(a),
        .b(b),
        .r(r)
    );

    initial begin
        clk = 0;
        forever #5 clk = ~clk;
    end
    
    initial begin
        $dumpfile("multiplier_tb.vcd");
        $dumpvars(0, multiplier_tb);
        // Inicialização
        set = 0;
        a = 0;
        b = 0;
        $display("Tempo: %0t | A: %0d | B: %0d | Set: %b | R: %0d", 
                  $time, a, b, set, r);

        
        // Teste 1: 3 * 5 = 15
        a = 4'd3;
        b = 4'd5;
        set = 1;
        #10;
        set = 0;

        #120;
        $display("Tempo: %0t | A: %0d | B: %0d | Set: %b | R: %0d", 
                  $time, a, b, set, r);

        // Teste 2: 7 * 2 = 14
        a = 4'd7;
        b = 4'd2;
        set = 1;
        #10;
        set = 0;
        #120;
        $display("Tempo: %0t | A: %0d | B: %0d | Set: %b | R: %0d", 
                  $time, a, b, set, r);

        // Teste 3: 0 * 9 = 0
        a = 4'd0;
        b = 4'd9;
        set = 1;
        #10;
        set = 0;
        #120;
        $display("Tempo: %0t | A: %0d | B: %0d | Set: %b | R: %0d", 
                  $time, a, b, set, r);   

        // Teste 4: 15 * 15 = 225
        a = 4'd15;
        b = 4'd15;
        set = 1;
        #10;
        set = 0;
        #120;
        $display("Tempo: %0t | A: %0d | B: %0d | Set: %b | R: %0d", 
                  $time, a, b, set, r);   

        // Teste 5: 1 * 12 = 12
        a = 4'd1;
        b = 4'd12;
        set = 1;
        #10;
        set = 0;
        #120;
        $display("Tempo: %0t | A: %0d | B: %0d | Set: %b | R: %0d", 
                  $time, a, b, set, r);   

        $finish;
    end

endmodule

lab04/multiplier_tb.vcd
$date
	Wed Apr 16 18:11:49 2025
$end
$version
	Icarus Verilog
$end
$timescale
	1ps
$end
$scope module multiplier_tb $end
$var wire 8 ! r [7:0] $end
$var parameter 32 " N $end
$var reg 4 # a [3:0] $end
$var reg 4 $ b [3:0] $end
$var reg 1 % clk $end
$var reg 1 & set $end
$scope module dut $end
$var wire 4 ' a [3:0] $end
$var wire 4 ( b [3:0] $end
$var wire 1 % clk $end
$var wire 1 & set $end
$var parameter 32 ) N $end
$var reg 8 * A_ext [7:0] $end
$var reg 4 + B [3:0] $end
$var reg 8 , r [7:0] $end
$upscope $end
$upscope $end
$enddefinitions $end
$comment Show the parameter values. $end
$dumpall
b100 )
b100 "
$end
#0
$dumpvars
bx ,
bx +
bx *
b101 (
b11 '
1&
0%
b101 $
b11 #
bx !
$end
#5000
b101 +
b11 *
b0 !
b0 ,
1%
#10000
0%
0&
#15000
b10 +
b110 *
b11 !
b11 ,
1%
#20000
0%
#25000
b1 +
b1100 *
1%
#30000
0%
#35000
b0 +
b11000 *
b1111 !
b1111 ,
1%
#40000
0%
#45000
b110000 *
1%
#50000
0%
#55000
b1100000 *
1%
#60000
0%
#65000
b11000000 *
1%
#70000
0%
#75000
b10000000 *
1%
#80000
0%
#85000
b0 *
1%
#90000
0%
#95000
1%
#100000
0%
#105000
1%
#110000
0%
#115000
1%
#120000
0%
#125000
1%
#130000
0%
1&
b10 $
b10 (
b111 #
b111 '
#135000
b10 +
b111 *
b0 !
b0 ,
1%
#140000
0%
0&
#145000
b1 +
b1110 *
1%
#150000
0%
#155000
b0 +
b11100 *
b1110 !
b1110 ,
1%
#160000
0%
#165000
b111000 *
1%
#170000
0%
#175000
b1110000 *
1%
#180000
0%
#185000
b11100000 *
1%
#190000
0%
#195000
b11000000 *
1%
#200000
0%
#205000
b10000000 *
1%
#210000
0%
#215000
b0 *
1%
#220000
0%
#225000
1%
#230000
0%
#235000
1%
#240000
0%
#245000
1%
#250000
0%
#255000
1%
#260000
0%
1&
b1001 $
b1001 (
b0 #
b0 '
#265000
b1001 +
b0 !
b0 ,
1%
#270000
0%
0&
#275000
b100 +
1%
#280000
0%
#285000
b10 +
1%
#290000
0%
#295000
b1 +
1%
#300000
0%
#305000
b0 +
1%
#310000
0%
#315000
1%
#320000
0%
#325000
1%
#330000
0%
#335000
1%
#340000
0%
#345000
1%
#350000
0%
#355000
1%
#360000
0%
#365000
1%
#370000
0%
#375000
1%
#380000
0%
#385000
1%
#390000
0%
1&
b1111 $
b1111 (
b1111 #
b1111 '
#395000
b1111 +
b1111 *
1%
#400000
0%
0&
#405000
b111 +
b11110 *
b1111 !
b1111 ,
1%
#410000
0%
#415000
b11 +
b111100 *
b101101 !
b101101 ,
1%
#420000
0%
#425000
b1 +
b1111000 *
b1101001 !
b1101001 ,
1%
#430000
0%
#435000
b0 +
b11110000 *
b11100001 !
b11100001 ,
1%
#440000
0%
#445000
b11100000 *
1%
#450000
0%
#455000
b11000000 *
1%
#460000
0%
#465000
b10000000 *
1%
#470000
0%
#475000
b0 *
1%
#480000
0%
#485000
1%
#490000
0%
#495000
1%
#500000
0%
#505000
1%
#510000
0%
#515000
1%
#520000
0%
1&
b1100 $
b1100 (
b1 #
b1 '
#525000
b1100 +
b1 *
b0 !
b0 ,
1%
#530000
0%
0&
#535000
b110 +
b10 *
1%
#540000
0%
#545000
b11 +
b100 *
1%
#550000
0%
#555000
b1 +
b1000 *
b100 !
b100 ,
1%
#560000
0%
#565000
b0 +
b10000 *
b1100 !
b1100 ,
1%
#570000
0%
#575000
b100000 *
1%
#580000
0%
#585000
b1000000 *
1%
#590000
0%
#595000
b10000000 *
1%
#600000
0%
#605000
b0 *
1%
