Lab01/ledshift.v
module ledshift (
    output wire [9:0] LEDR,  
    input [3:0] KEY,                        
    input CLOCK_50                         
);

    reg [9:0] registrador;  // Registrador para armazenar o estado dos LEDs
	 reg [2:0] detector_dir, detector_esq;
	 wire fiozinho, fiozao;
	 
	 initial begin
		registrador = 10'b0000100000;
		detector_esq = 3'b000;
		detector_dir = 3'b000;
	 end
	 
	 assign fiozinho = ~detector_dir[2] & detector_dir[1];
	 assign fiozao = ~detector_esq[2] & detector_esq[1];


	always @(posedge CLOCK_50) begin
			detector_dir <= {detector_dir[1:0], ~KEY[0]};
			detector_esq <= {detector_esq[1:0], ~KEY[3]};
	end
	 
	 
    always @(posedge CLOCK_50) begin
        if (registrador[0] == 1'b0 && fiozinho) begin
            registrador <= registrador >> 1;
        end

        if (registrador[9] == 1'b0 && fiozao) begin
            registrador <= registrador << 1;
        end

 
    end

	 
	 assign LEDR = registrador;  
endmodule

Lab01/ledshift_tb.v
`timescale 1ns/1ps

module ledshift_tb();
    reg [3:0] KEY;
    reg CLOCK_50;
    wire [9:0] LEDR;

    // Instanciando o módulo a ser testado
    ledshift uut (
        .LEDR(LEDR),
        .KEY(KEY),
        .CLOCK_50(CLOCK_50)
    );

    // Geração de clock usando always
    initial begin
        CLOCK_50 = 1'b0;
    end

	 always #2 CLOCK_50 = ~CLOCK_50;
	 
	 integer i;
	 
    // Teste principals
    initial begin
        $dumpfile("ledshift_tb.vcd"); // Arquivo de saída para waveform
        $dumpvars(0, ledshift_tb);    // Salvar variáveis no waveform

        // Inicialização
        KEY = 4'b1111; // Nenhuma tecla pressionada

		  for (i=0; i<10; i=i+1)
		  begin
				KEY[3] = 0; // Pressiona KEY[0] (movimento para direita)
				#20;
				KEY[3] = 1; // Solta KEY[0]
				#20;
		  end
		  for (i=0; i<10; i=i+1)
		  begin
				KEY[0] = 0; // Pressiona KEY[0] (movimento para direita)
				#20;
				KEY[0] = 1; // Solta KEY[0]
				#20;
		  end


		  
        $finish; // Finaliza a simulação
		  
    end

endmodule

Lab01/simulation/modelsim/ledshift_tb.vcd
$date
	Wed Mar 26 14:09:12 2025
$end
$version
	ModelSim Version 10.5b
$end
$timescale
	1ps
$end

$scope module ledshift_tb $end
$var reg 4 ! KEY [3:0] $end
$var reg 1 " CLOCK_50 $end
$var wire 1 # LEDR [9] $end
$var wire 1 $ LEDR [8] $end
$var wire 1 % LEDR [7] $end
$var wire 1 & LEDR [6] $end
$var wire 1 ' LEDR [5] $end
$var wire 1 ( LEDR [4] $end
$var wire 1 ) LEDR [3] $end
$var wire 1 * LEDR [2] $end
$var wire 1 + LEDR [1] $end
$var wire 1 , LEDR [0] $end
$var integer 32 - i $end

$scope module uut $end
$var wire 1 # LEDR [9] $end
$var wire 1 $ LEDR [8] $end
$var wire 1 % LEDR [7] $end
$var wire 1 & LEDR [6] $end
$var wire 1 ' LEDR [5] $end
$var wire 1 ( LEDR [4] $end
$var wire 1 ) LEDR [3] $end
$var wire 1 * LEDR [2] $end
$var wire 1 + LEDR [1] $end
$var wire 1 , LEDR [0] $end
$var wire 1 . KEY [3] $end
$var wire 1 / KEY [2] $end
$var wire 1 0 KEY [1] $end
$var wire 1 1 KEY [0] $end
$var wire 1 2 CLOCK_50 $end
$var reg 10 3 registrador [9:0] $end
$var reg 3 4 detector_dir [2:0] $end
$var reg 3 5 detector_esq [2:0] $end
$var wire 1 6 fiozinho $end
$var wire 1 7 fiozao $end
$upscope $end
$upscope $end
$enddefinitions $end
#0
$dumpvars
b111 !
0"
b100000 3
b0 4
b0 5
b0 -
0,
0+
0*
0)
0(
1'
0&
0%
0$
0#
06
07
02
11
10
1/
0.
$end
#2000
1"
12
b1 5
#4000
0"
02
#6000
1"
12
b11 5
17
#8000
0"
02
#10000
1"
12
b111 5
b1000000 3
07
0'
1&
#12000
0"
02
#14000
1"
12
#16000
0"
02
#18000
1"
12
#20000
b1111 !
0"
1.
02
#22000
1"
12
b110 5
#24000
0"
02
#26000
1"
12
b100 5
#28000
0"
02
#30000
1"
12
b0 5
#32000
0"
02
#34000
1"
12
#36000
0"
02
#38000
1"
12
#40000
b1 -
b111 !
0"
0.
02
#42000
1"
12
b1 5
#44000
0"
02
#46000
1"
12
b11 5
17
#48000
0"
02
#50000
1"
12
b111 5
b10000000 3
07
0&
1%
#52000
0"
02
#54000
1"
12
#56000
0"
02
#58000
1"
12
#60000
b1111 !
0"
1.
02
#62000
1"
12
b110 5
#64000
0"
02
#66000
1"
12
b100 5
#68000
0"
02
#70000
1"
12
b0 5
#72000
0"
02
#74000
1"
12
#76000
0"
02
#78000
1"
12
#80000
b10 -
b111 !
0"
0.
02
#82000
1"
12
b1 5
#84000
0"
02
#86000
1"
12
b11 5
17
#88000
0"
02
#90000
1"
12
b111 5
b100000000 3
07
0%
1$
#92000
0"
02
#94000
1"
12
#96000
0"
02
#98000
1"
12
#100000
b1111 !
0"
1.
02
#102000
1"
12
b110 5
#104000
0"
02
#106000
1"
12
b100 5
#108000
0"
02
#110000
1"
12
b0 5
#112000
0"
02
#114000
1"
12
#116000
0"
02
#118000
1"
12
#120000
b11 -
b111 !
0"
0.
02
#122000
1"
12
b1 5
#124000
0"
02
#126000
1"
12
b11 5
17
#128000
0"
02
#130000
1"
12
b111 5
b1000000000 3
07
0$
1#
#132000
0"
02
#134000
1"
12
#136000
0"
02
#138000
1"
12
#140000
b1111 !
0"
1.
02
#142000
1"
12
b110 5
#144000
0"
02
#146000
1"
12
b100 5
#148000
0"
02
#150000
1"
12
b0 5
#152000
0"
02
#154000
1"
12
#156000
0"
02
#158000
1"
12
#160000
b100 -
b111 !
0"
0.
02
#162000
1"
12
b1 5
#164000
0"
02
#166000
1"
12
b11 5
17
#168000
0"
02
#170000
1"
12
b111 5
07
#172000
0"
02
#174000
1"
12
#176000
0"
02
#178000
1"
12
#180000
b1111 !
0"
1.
02
#182000
1"
12
b110 5
#184000
0"
02
#186000
1"
12
b100 5
#188000
0"
02
#190000
1"
12
b0 5
#192000
0"
02
#194000
1"
12
#196000
0"
02
#198000
1"
12
#200000
b101 -
b111 !
0"
0.
02
#202000
1"
12
b1 5
#204000
0"
02
#206000
1"
12
b11 5
17
#208000
0"
02
#210000
1"
12
b111 5
07
#212000
0"
02
#214000
1"
12
#216000
0"
02
#218000
1"
12
#220000
b1111 !
0"
1.
02
#222000
1"
12
b110 5
#224000
0"
02
#226000
1"
12
b100 5
#228000
0"
02
#230000
1"
12
b0 5
#232000
0"
02
#234000
1"
12
#236000
0"
02
#238000
1"
12
#240000
b110 -
b111 !
0"
0.
02
#242000
1"
12
b1 5
#244000
0"
02
#246000
1"
12
b11 5
17
#248000
0"
02
#250000
1"
12
b111 5
07
#252000
0"
02
#254000
1"
12
#256000
0"
02
#258000
1"
12
#260000
b1111 !
0"
1.
02
#262000
1"
12
b110 5
#264000
0"
02
#266000
1"
12
b100 5
#268000
0"
02
#270000
1"
12
b0 5
#272000
0"
02
#274000
1"
12
#276000
0"
02
#278000
1"
12
#280000
b111 -
b111 !
0"
0.
02
#282000
1"
12
b1 5
#284000
0"
02
#286000
1"
12
b11 5
17
#288000
0"
02
#290000
1"
12
b111 5
07
#292000
0"
02
#294000
1"
12
#296000
0"
02
#298000
1"
12
#300000
b1111 !
0"
1.
02
#302000
1"
12
b110 5
#304000
0"
02
#306000
1"
12
b100 5
#308000
0"
02
#310000
1"
12
b0 5
#312000
0"
02
#314000
1"
12
#316000
0"
02
#318000
1"
12
#320000
b1000 -
b111 !
0"
0.
02
#322000
1"
12
b1 5
#324000
0"
02
#326000
1"
12
b11 5
17
#328000
0"
02
#330000
1"
12
b111 5
07
#332000
0"
02
#334000
1"
12
#336000
0"
02
#338000
1"
12
#340000
b1111 !
0"
1.
02
#342000
1"
12
b110 5
#344000
0"
02
#346000
1"
12
b100 5
#348000
0"
02
#350000
1"
12
b0 5
#352000
0"
02
#354000
1"
12
#356000
0"
02
#358000
1"
12
#360000
b1001 -
b111 !
0"
0.
02
#362000
1"
12
b1 5
#364000
0"
02
#366000
1"
12
b11 5
17
#368000
0"
02
#370000
1"
12
b111 5
07
#372000
0"
02
#374000
1"
12
#376000
0"
02
#378000
1"
12
#380000
b1111 !
0"
1.
02
#382000
1"
12
b110 5
#384000
0"
02
#386000
1"
12
b100 5
#388000
0"
02
#390000
1"
12
b0 5
#392000
0"
02
#394000
1"
12
#396000
0"
02
#398000
1"
12
#400000
b1010 -
b0 -
b1110 !
0"
01
02
#402000
1"
12
b1 4
#404000
0"
02
#406000
1"
12
b11 4
16
#408000
0"
02
#410000
1"
12
b111 4
b100000000 3
06
1$
0#
#412000
0"
02
#414000
1"
12
#416000
0"
02
#418000
1"
12
#420000
b1111 !
0"
11
02
#422000
1"
12
b110 4
#424000
0"
02
#426000
1"
12
b100 4
#428000
0"
02
#430000
1"
12
b0 4
#432000
0"
02
#434000
1"
12
#436000
0"
02
#438000
1"
12
#440000
b1 -
b1110 !
0"
01
02
#442000
1"
12
b1 4
#444000
0"
02
#446000
1"
12
b11 4
16
#448000
0"
02
#450000
1"
12
b111 4
b10000000 3
06
1%
0$
#452000
0"
02
#454000
1"
12
#456000
0"
02
#458000
1"
12
#460000
b1111 !
0"
11
02
#462000
1"
12
b110 4
#464000
0"
02
#466000
1"
12
b100 4
#468000
0"
02
#470000
1"
12
b0 4
#472000
0"
02
#474000
1"
12
#476000
0"
02
#478000
1"
12
#480000
b10 -
b1110 !
0"
01
02
#482000
1"
12
b1 4
#484000
0"
02
#486000
1"
12
b11 4
16
#488000
0"
02
#490000
1"
12
b111 4
b1000000 3
06
1&
0%
#492000
0"
02
#494000
1"
12
#496000
0"
02
#498000
1"
12
#500000
b1111 !
0"
11
02
#502000
1"
12
b110 4
#504000
0"
02
#506000
1"
12
b100 4
#508000
0"
02
#510000
1"
12
b0 4
#512000
0"
02
#514000
1"
12
#516000
0"
02
#518000
1"
12
#520000
b11 -
b1110 !
0"
01
02
#522000
1"
12
b1 4
#524000
0"
02
#526000
1"
12
b11 4
16
#528000
0"
02
#530000
1"
12
b111 4
b100000 3
06
1'
0&
#532000
0"
02
#534000
1"
12
#536000
0"
02
#538000
1"
12
#540000
b1111 !
0"
11
02
#542000
1"
12
b110 4
#544000
0"
02
#546000
1"
12
b100 4
#548000
0"
02
#550000
1"
12
b0 4
#552000
0"
02
#554000
1"
12
#556000
0"
02
#558000
1"
12
#560000
b100 -
b1110 !
0"
01
02
#562000
1"
12
b1 4
#564000
0"
02
#566000
1"
12
b11 4
16
#568000
0"
02
#570000
1"
12
b111 4
b10000 3
06
1(
0'
#572000
0"
02
#574000
1"
12
#576000
0"
02
#578000
1"
12
#580000
b1111 !
0"
11
02
#582000
1"
12
b110 4
#584000
0"
02
#586000
1"
12
b100 4
#588000
0"
02
#590000
1"
12
b0 4
#592000
0"
02
#594000
1"
12
#596000
0"
02
#598000
1"
12
#600000
b101 -
b1110 !
0"
01
02
#602000
1"
12
b1 4
#604000
0"
02
#606000
1"
12
b11 4
16
#608000
0"
02
#610000
1"
12
b111 4
b1000 3
06
1)
0(
#612000
0"
02
#614000
1"
12
#616000
0"
02
#618000
1"
12
#620000
b1111 !
0"
11
02
#622000
1"
12
b110 4
#624000
0"
02
#626000
1"
12
b100 4
#628000
0"
02
#630000
1"
12
b0 4
#632000
0"
02
#634000
1"
12
#636000
0"
02
#638000
1"
12
#640000
b110 -
b1110 !
0"
01
02
#642000
1"
12
b1 4
#644000
0"
02
#646000
1"
12
b11 4
16
#648000
0"
02
#650000
1"
12
b111 4
b100 3
06
1*
0)
#652000
0"
02
#654000
1"
12
#656000
0"
02
#658000
1"
12
#660000
b1111 !
0"
11
02
#662000
1"
12
b110 4
#664000
0"
02
#666000
1"
12
b100 4
#668000
0"
02
#670000
1"
12
b0 4
#672000
0"
02
#674000
1"
12
#676000
0"
02
#678000
1"
12
#680000
b111 -
b1110 !
0"
01
02
#682000
1"
12
b1 4
#684000
0"
02
#686000
1"
12
b11 4
16
#688000
0"
02
#690000
1"
12
b111 4
b10 3
06
1+
0*
#692000
0"
02
#694000
1"
12
#696000
0"
02
#698000
1"
12
#700000
b1111 !
0"
11
02
#702000
1"
12
b110 4
#704000
0"
02
#706000
1"
12
b100 4
#708000
0"
02
#710000
1"
12
b0 4
#712000
0"
02
#714000
1"
12
#716000
0"
02
#718000
1"
12
#720000
b1000 -
b1110 !
0"
01
02
#722000
1"
12
b1 4
#724000
0"
02
#726000
1"
12
b11 4
16
#728000
0"
02
#730000
1"
12
b111 4
b1 3
06
1,
0+
#732000
0"
02
#734000
1"
12
#736000
0"
02
#738000
1"
12
#740000
b1111 !
0"
11
02
#742000
1"
12
b110 4
#744000
0"
02
#746000
1"
12
b100 4
#748000
0"
02
#750000
1"
12
b0 4
#752000
0"
02
#754000
1"
12
#756000
0"
02
#758000
1"
12
#760000
b1001 -
b1110 !
0"
01
02
#762000
1"
12
b1 4
#764000
0"
02
#766000
1"
12
b11 4
16
#768000
0"
02
#770000
1"
12
b111 4
06
#772000
0"
02
#774000
1"
12
#776000
0"
02
#778000
1"
12
#780000
b1111 !
0"
11
02
#782000
1"
12
b110 4
#784000
0"
02
#786000
1"
12
b100 4
#788000
0"
02
#790000
1"
12
b0 4
#792000
0"
02
#794000
1"
12
#796000
0"
02
#798000
1"
12
#800000
b1010 -
